{
    "Header": {
        "TimeStamp": "14-Apr-2024 - 11:46:01",
        "Program": "GeniE - D8.10-00",
        "Workspace": "EMULF2_DeltaFloater"
    },
    "EngineeringLimitsTolerances": {
        "Tolerance": 0.01,
        "Beta": 45.0,
        "BetaWarning": 5.0
    },
    "BucklingModels": [
        {
            "Id": 1,
            "Name": "panel(Pl563, Pl482, 4)_to_(Pl563, Pl482, 1)",
            "Type": 1,
            "Plates": [
                {
                    "Id": 0,
                    "Name": "Plate(Pl563, Pl482, 4)",
                    "Type": 0,
                    "Material": {
                        "E": 210000000000.0,
                        "G": 80769230769.23077,
                        "fy": 355000000.0,
                        "GammaM": 1.15,
                        "PoissonRatio": 0.3
                    },
                    "Geometry": {
                        "Thickness": 0.03249999999883889,
                        "Length": 4.0,
                        "Width": 1.7500000004839356
                    },
                    "FiniteElements": [
                        28389,
                        28390,
                        28391,
                        28392,
                        32158,
                        32159,
                        32160,
                        32161,
                        32162
                    ]
                },
                {
                    "Id": 1,
                    "Name": "Plate(Pl563, Pl482, 3)",
                    "Type": 0,
                    "Material": {
                        "E": 210000000000.0,
                        "G": 80769230769.23077,
                        "fy": 355000000.0,
                        "GammaM": 1.15,
                        "PoissonRatio": 0.3
                    },
                    "Geometry": {
                        "Thickness": 0.03249999766789552,
                        "Length": 4.000000000000024,
                        "Width": 1.7499989116860857
                    },
                    "FiniteElements": [
                        28385,
                        28386,
                        28387,
                        28388,
                        32154,
                        32155,
                        32156,
                        32157
                    ]
                },
                {
                    "Id": 2,
                    "Name": "Plate(Pl563, Pl482, 2)",
                    "Type": 0,
                    "Material": {
                        "E": 210000000000.0,
                        "G": 80769230769.23077,
                        "fy": 355000000.0,
                        "GammaM": 1.15,
                        "PoissonRatio": 0.3
                    },
                    "Geometry": {
                        "Thickness": 0.03250000233210303,
                        "Length": 4.00000000000002,
                        "Width": 1.7500010883139625
                    },
                    "FiniteElements": [
                        28381,
                        28382,
                        28383,
                        28384,
                        32149,
                        32150,
                        32151,
                        32152,
                        32153
                    ]
                },
                {
                    "Id": 3,
                    "Name": "Plate(Pl563, Pl482, 1)",
                    "Type": 0,
                    "Material": {
                        "E": 210000000000.0,
                        "G": 80769230769.23077,
                        "fy": 355000000.0,
                        "GammaM": 1.15,
                        "PoissonRatio": 0.3
                    },
                    "Geometry": {
                        "Thickness": 0.03250000000081099,
                        "Length": 4.0000000000000036,
                        "Width": 1.7499967356517392
                    },
                    "FiniteElements": [
                        28377,
                        28378,
                        28379,
                        28380,
                        32144,
                        32145,
                        32146,
                        32147,
                        32148
                    ]
                }
            ],
            "Stiffeners": [
                {
                    "Id": 4,
                    "Name": "Stiffener(Pl563, Pl482, 4)",
                    "Type": 1,
                    "StiffenerType": 0,
                    "StiffenerFunction": 0,
                    "StiffenerConnection": 1,
                    "SupportAtFirstCrossSection": 0,
                    "SupportAtSecondCrossSection": 0,
                    "Material": {
                        "E": 210000000000.0,
                        "G": 80769230769.23077,
                        "fy": 355000000.0,
                        "GammaM": 1.15,
                        "PoissonRatio": 0.3
                    },
                    "StiffenerSections": [
                        {
                            "ConnectionNodeId": 16886,
                            "ConnectedSections": [
                                {
                                    "SectionId": 1,
                                    "Orientation": {
                                        "X": 1.0,
                                        "Y": 7.780498467e-12,
                                        "Z": -1.863718069048638e-10
                                    },
                                    "Eccentricity": {
                                        "X": 0.0,
                                        "Y": 0.0,
                                        "Z": 0.0
                                    }
                                }
                            ]
                        },
                        {
                            "ConnectionNodeId": 16944,
                            "ConnectedSections": [
                                {
                                    "SectionId": 1,
                                    "Orientation": {
                                        "X": 1.0,
                                        "Y": 7.780498467e-12,
                                        "Z": -1.863718069048638e-10
                                    },
                                    "Eccentricity": {
                                        "X": 0.0,
                                        "Y": 0.0,
                                        "Z": 0.0
                                    }
                                }
                            ]
                        },
                        {
                            "ConnectionNodeId": 16945,
                            "ConnectedSections": [
                                {
                                    "SectionId": 1,
                                    "Orientation": {
                                        "X": 1.0,
                                        "Y": 7.780498467e-12,
                                        "Z": -1.863718069048638e-10
                                    },
                                    "Eccentricity": {
                                        "X": 0.0,
                                        "Y": 0.0,
                                        "Z": 0.0
                                    }
                                }
                            ]
                        },
                        {
                            "ConnectionNodeId": 16946,
                            "ConnectedSections": [
                                {
                                    "SectionId": 1,
                                    "Orientation": {
                                        "X": 1.0,
                                        "Y": 7.780498467e-12,
                                        "Z": -1.863718069048638e-10
                                    },
                                    "Eccentricity": {
                                        "X": 0.0,
                                        "Y": 0.0,
                                        "Z": 0.0
                                    }
                                }
                            ]
                        },
                        {
                            "ConnectionNodeId": 16947,
                            "ConnectedSections": [
                                {
                                    "SectionId": 1,
                                    "Orientation": {
                                        "X": 1.0,
                                        "Y": 7.780498467e-12,
                                        "Z": -1.863718069048638e-10
                                    },
                                    "Eccentricity": {
                                        "X": 0.0,
                                        "Y": 0.0,
                                        "Z": 0.0
                                    }
                                }
                            ]
                        }
                    ],
                    "Sections": [
                        {
                            "SectionId": 1,
                            "SectionName": "BSRAbulb400x16x58x18x18x4_Lump3_333",
                            "SectionType": 7,
                            "SectionParameters": {
                                "FilletRadius": 0.0,
                                "FilletRadiusInner": 0.0,
                                "FlangeThickness": 0.04393665239,
                                "FlangeThicknessBottom": -1.7976931348623157e+308,
                                "FlangeThicknessTop": -1.7976931348623157e+308,
                                "FlangeWidth": 0.246642,
                                "FlangeWidthBottom": -1.7976931348623157e+308,
                                "FlangeWidthBottomOffset": -1.7976931348623157e+308,
                                "FlangeWidthTop": -1.7976931348623157e+308,
                                "FlangeWidthTopOffset": -1.7976931348623157e+308,
                                "Height": 0.4,
                                "OuterDiameter": -1.7976931348623157e+308,
                                "OuterWebThickness": -1.7976931348623157e+308,
                                "Thickness": -1.7976931348623157e+308,
                                "WebSpacing": -1.7976931348623157e+308,
                                "WebThickness": 0.053328,
                                "Width": -1.7976931348623157e+308,
                                "WebOrientation": 0
                            },
                            "SectionGeneral": {
                                "Comp": 0,
                                "Area": 0.02982477002012046,
                                "Ix": 2.4232536525549114e-05,
                                "Iy": 0.00047832325666986007,
                                "Iz": 0.00012389110721570783,
                                "Iyz": -0.0001333714178990313,
                                "Wxmin": 0.0004205650000017579,
                                "Wymin": 0.0019079485579935117,
                                "Wzmin": 0.0006701948202727927,
                                "Shary": 0.007250901331254434,
                                "Sharz": 0.015220952145599072,
                                "Shceny": -0.03511965214634183,
                                "Shcenz": -0.12733138387009357,
                                "Sy": 0.0016758493415975682,
                                "Sz": 0.0007507150164194901,
                                "Wpy": 0.0,
                                "Wpz": 0.0,
                                "Fabr": 0
                            }
                        }
                    ],
                    "FiniteElements": [
                        16985,
                        16986,
                        16987,
                        16988
                    ]
                },
                {
                    "Id": 5,
                    "Name": "Stiffener(Pl563, Pl482, 3)",
                    "Type": 1,
                    "StiffenerType": 0,
                    "StiffenerFunction": 0,
                    "StiffenerConnection": 1,
                    "SupportAtFirstCrossSection": 0,
                    "SupportAtSecondCrossSection": 0,
                    "Material": {
                        "E": 210000000000.0,
                        "G": 80769230769.23077,
                        "fy": 355000000.0,
                        "GammaM": 1.15,
                        "PoissonRatio": 0.3
                    },
                    "StiffenerSections": [
                        {
                            "ConnectionNodeId": 16890,
                            "ConnectedSections": [
                                {
                                    "SectionId": 2,
                                    "Orientation": {
                                        "X": 1.0,
                                        "Y": 7.780167974999871e-12,
                                        "Z": -1.0280381032384968e-09
                                    },
                                    "Eccentricity": {
                                        "X": 0.0,
                                        "Y": 0.0,
                                        "Z": 0.0
                                    }
                                }
                            ]
                        },
                        {
                            "ConnectionNodeId": 16948,
                            "ConnectedSections": [
                                {
                                    "SectionId": 2,
                                    "Orientation": {
                                        "X": 1.0,
                                        "Y": 7.780167974999871e-12,
                                        "Z": -1.0280381032384968e-09
                                    },
                                    "Eccentricity": {
                                        "X": 0.0,
                                        "Y": 0.0,
                                        "Z": 0.0
                                    }
                                }
                            ]
                        },
                        {
                            "ConnectionNodeId": 16949,
                            "ConnectedSections": [
                                {
                                    "SectionId": 2,
                                    "Orientation": {
                                        "X": 1.0,
                                        "Y": 7.780167974999871e-12,
                                        "Z": -1.0280381032384968e-09
                                    },
                                    "Eccentricity": {
                                        "X": 0.0,
                                        "Y": 0.0,
                                        "Z": 0.0
                                    }
                                }
                            ]
                        },
                        {
                            "ConnectionNodeId": 16950,
                            "ConnectedSections": [
                                {
                                    "SectionId": 2,
                                    "Orientation": {
                                        "X": 1.0,
                                        "Y": 7.780167974999871e-12,
                                        "Z": -1.0280381032384968e-09
                                    },
                                    "Eccentricity": {
                                        "X": 0.0,
                                        "Y": 0.0,
                                        "Z": 0.0
                                    }
                                }
                            ]
                        },
                        {
                            "ConnectionNodeId": 16951,
                            "ConnectedSections": [
                                {
                                    "SectionId": 2,
                                    "Orientation": {
                                        "X": 1.0,
                                        "Y": 7.780167974999871e-12,
                                        "Z": -1.0280381032384968e-09
                                    },
                                    "Eccentricity": {
                                        "X": 0.0,
                                        "Y": 0.0,
                                        "Z": 0.0
                                    }
                                }
                            ]
                        }
                    ],
                    "Sections": [
                        {
                            "SectionId": 2,
                            "SectionName": "BSRAbulb400x16x58x18x18x4_Lump3_333",
                            "SectionType": 7,
                            "SectionParameters": {
                                "FilletRadius": 0.0,
                                "FilletRadiusInner": 0.0,
                                "FlangeThickness": 0.04393665239,
                                "FlangeThicknessBottom": -1.7976931348623157e+308,
                                "FlangeThicknessTop": -1.7976931348623157e+308,
                                "FlangeWidth": 0.246642,
                                "FlangeWidthBottom": -1.7976931348623157e+308,
                                "FlangeWidthBottomOffset": -1.7976931348623157e+308,
                                "FlangeWidthTop": -1.7976931348623157e+308,
                                "FlangeWidthTopOffset": -1.7976931348623157e+308,
                                "Height": 0.4,
                                "OuterDiameter": -1.7976931348623157e+308,
                                "OuterWebThickness": -1.7976931348623157e+308,
                                "Thickness": -1.7976931348623157e+308,
                                "WebSpacing": -1.7976931348623157e+308,
                                "WebThickness": 0.053328,
                                "Width": -1.7976931348623157e+308,
                                "WebOrientation": 0
                            },
                            "SectionGeneral": {
                                "Comp": 0,
                                "Area": 0.02982477002012046,
                                "Ix": 2.4232536525549114e-05,
                                "Iy": 0.00047832325666986007,
                                "Iz": 0.00012389110721570783,
                                "Iyz": -0.0001333714178990313,
                                "Wxmin": 0.0004205650000017579,
                                "Wymin": 0.0019079485579935117,
                                "Wzmin": 0.0006701948202727927,
                                "Shary": 0.007250901331254434,
                                "Sharz": 0.015220952145599072,
                                "Shceny": -0.03511965214634183,
                                "Shcenz": -0.12733138387009357,
                                "Sy": 0.0016758493415975682,
                                "Sz": 0.0007507150164194901,
                                "Wpy": 0.0,
                                "Wpz": 0.0,
                                "Fabr": 0
                            }
                        }
                    ],
                    "FiniteElements": [
                        16989,
                        16990,
                        16991,
                        16992
                    ]
                },
                {
                    "Id": 6,
                    "Name": "Stiffener(Pl563, Pl482, 2)",
                    "Type": 1,
                    "StiffenerType": 0,
                    "StiffenerFunction": 0,
                    "StiffenerConnection": 1,
                    "SupportAtFirstCrossSection": 0,
                    "SupportAtSecondCrossSection": 0,
                    "Material": {
                        "E": 210000000000.0,
                        "G": 80769230769.23077,
                        "fy": 355000000.0,
                        "GammaM": 1.15,
                        "PoissonRatio": 0.3
                    },
                    "StiffenerSections": [
                        {
                            "ConnectionNodeId": 16894,
                            "ConnectedSections": [
                                {
                                    "SectionId": 3,
                                    "Orientation": {
                                        "X": 1.0,
                                        "Y": 7.780498467e-12,
                                        "Z": -1.863718069048638e-10
                                    },
                                    "Eccentricity": {
                                        "X": 0.0,
                                        "Y": 0.0,
                                        "Z": 0.0
                                    }
                                }
                            ]
                        },
                        {
                            "ConnectionNodeId": 16952,
                            "ConnectedSections": [
                                {
                                    "SectionId": 3,
                                    "Orientation": {
                                        "X": 1.0,
                                        "Y": 7.780498467e-12,
                                        "Z": -1.863718069048638e-10
                                    },
                                    "Eccentricity": {
                                        "X": 0.0,
                                        "Y": 0.0,
                                        "Z": 0.0
                                    }
                                }
                            ]
                        },
                        {
                            "ConnectionNodeId": 16953,
                            "ConnectedSections": [
                                {
                                    "SectionId": 3,
                                    "Orientation": {
                                        "X": 1.0,
                                        "Y": 7.780498467e-12,
                                        "Z": -1.863718069048638e-10
                                    },
                                    "Eccentricity": {
                                        "X": 0.0,
                                        "Y": 0.0,
                                        "Z": 0.0
                                    }
                                }
                            ]
                        },
                        {
                            "ConnectionNodeId": 16954,
                            "ConnectedSections": [
                                {
                                    "SectionId": 3,
                                    "Orientation": {
                                        "X": 1.0,
                                        "Y": 7.780498467e-12,
                                        "Z": -1.863718069048638e-10
                                    },
                                    "Eccentricity": {
                                        "X": 0.0,
                                        "Y": 0.0,
                                        "Z": 0.0
                                    }
                                }
                            ]
                        },
                        {
                            "ConnectionNodeId": 16955,
                            "ConnectedSections": [
                                {
                                    "SectionId": 3,
                                    "Orientation": {
                                        "X": 1.0,
                                        "Y": 7.780498467e-12,
                                        "Z": -1.863718069048638e-10
                                    },
                                    "Eccentricity": {
                                        "X": 0.0,
                                        "Y": 0.0,
                                        "Z": 0.0
                                    }
                                }
                            ]
                        }
                    ],
                    "Sections": [
                        {
                            "SectionId": 3,
                            "SectionName": "BSRAbulb400x16x58x18x18x4_Lump3_333",
                            "SectionType": 7,
                            "SectionParameters": {
                                "FilletRadius": 0.0,
                                "FilletRadiusInner": 0.0,
                                "FlangeThickness": 0.04393665239,
                                "FlangeThicknessBottom": -1.7976931348623157e+308,
                                "FlangeThicknessTop": -1.7976931348623157e+308,
                                "FlangeWidth": 0.246642,
                                "FlangeWidthBottom": -1.7976931348623157e+308,
                                "FlangeWidthBottomOffset": -1.7976931348623157e+308,
                                "FlangeWidthTop": -1.7976931348623157e+308,
                                "FlangeWidthTopOffset": -1.7976931348623157e+308,
                                "Height": 0.4,
                                "OuterDiameter": -1.7976931348623157e+308,
                                "OuterWebThickness": -1.7976931348623157e+308,
                                "Thickness": -1.7976931348623157e+308,
                                "WebSpacing": -1.7976931348623157e+308,
                                "WebThickness": 0.053328,
                                "Width": -1.7976931348623157e+308,
                                "WebOrientation": 0
                            },
                            "SectionGeneral": {
                                "Comp": 0,
                                "Area": 0.02982477002012046,
                                "Ix": 2.4232536525549114e-05,
                                "Iy": 0.00047832325666986007,
                                "Iz": 0.00012389110721570783,
                                "Iyz": -0.0001333714178990313,
                                "Wxmin": 0.0004205650000017579,
                                "Wymin": 0.0019079485579935117,
                                "Wzmin": 0.0006701948202727927,
                                "Shary": 0.007250901331254434,
                                "Sharz": 0.015220952145599072,
                                "Shceny": -0.03511965214634183,
                                "Shcenz": -0.12733138387009357,
                                "Sy": 0.0016758493415975682,
                                "Sz": 0.0007507150164194901,
                                "Wpy": 0.0,
                                "Wpz": 0.0,
                                "Fabr": 0
                            }
                        }
                    ],
                    "FiniteElements": [
                        16993,
                        16994,
                        16995,
                        16996
                    ]
                }
            ],
            "Connections": [
                {
                    "Id": 0,
                    "Name": "Connection1",
                    "Type": 0,
                    "FiniteElementNodes": [
                        16886,
                        16944,
                        16945,
                        16946,
                        16947
                    ],
                    "FiniteElementNodeTransformations": [
                        {
                            "NodeNumber": 16886,
                            "Type": 1,
                            "T": [
                                1.863718069e-10,
                                7.780498583505868e-12,
                                1.0,
                                6.25126025e-10,
                                -1.0,
                                7.780498467e-12,
                                1.0,
                                6.251260249985499e-10,
                                -1.863718069048638e-10
                            ]
                        },
                        {
                            "NodeNumber": 16944,
                            "Type": 1,
                            "T": [
                                1.863718069e-10,
                                7.780498583505868e-12,
                                1.0,
                                6.25126025e-10,
                                -1.0,
                                7.780498467e-12,
                                1.0,
                                6.251260249985499e-10,
                                -1.863718069048638e-10
                            ]
                        },
                        {
                            "NodeNumber": 16945,
                            "Type": 1,
                            "T": [
                                1.863718069e-10,
                                7.780498583505868e-12,
                                1.0,
                                6.25126025e-10,
                                -1.0,
                                7.780498467e-12,
                                1.0,
                                6.251260249985499e-10,
                                -1.863718069048638e-10
                            ]
                        },
                        {
                            "NodeNumber": 16946,
                            "Type": 1,
                            "T": [
                                1.863718069e-10,
                                7.780498583505868e-12,
                                1.0,
                                6.25126025e-10,
                                -1.0,
                                7.780498467e-12,
                                1.0,
                                6.251260249985499e-10,
                                -1.863718069048638e-10
                            ]
                        },
                        {
                            "NodeNumber": 16947,
                            "Type": 1,
                            "T": [
                                1.863718069e-10,
                                7.780498583505868e-12,
                                1.0,
                                6.25126025e-10,
                                -1.0,
                                7.780498467e-12,
                                1.0,
                                6.251260249985499e-10,
                                -1.863718069048638e-10
                            ]
                        }
                    ],
                    "Entities": [
                        0,
                        1,
                        4
                    ],
                    "EntityTypes": [
                        0,
                        0,
                        1
                    ]
                },
                {
                    "Id": 1,
                    "Name": "Connection2",
                    "Type": 0,
                    "FiniteElementNodes": [
                        16890,
                        16948,
                        16949,
                        16950,
                        16951
                    ],
                    "FiniteElementNodeTransformations": [
                        {
                            "NodeNumber": 16890,
                            "Type": 1,
                            "T": [
                                1.0280380989998476e-09,
                                7.780728031815311e-12,
                                1.0,
                                5.447821581999192e-07,
                                -0.9999999999998517,
                                7.780167974999871e-12,
                                0.9999999999998517,
                                5.447821581999111e-07,
                                -1.0280381032384968e-09
                            ]
                        },
                        {
                            "NodeNumber": 16948,
                            "Type": 1,
                            "T": [
                                1.0280380989998476e-09,
                                7.780728031815311e-12,
                                1.0,
                                5.447821581999192e-07,
                                -0.9999999999998517,
                                7.780167974999871e-12,
                                0.9999999999998517,
                                5.447821581999111e-07,
                                -1.0280381032384968e-09
                            ]
                        },
                        {
                            "NodeNumber": 16949,
                            "Type": 1,
                            "T": [
                                1.0280380989998476e-09,
                                7.780728031815311e-12,
                                1.0,
                                5.447821581999192e-07,
                                -0.9999999999998517,
                                7.780167974999871e-12,
                                0.9999999999998517,
                                5.447821581999111e-07,
                                -1.0280381032384968e-09
                            ]
                        },
                        {
                            "NodeNumber": 16950,
                            "Type": 1,
                            "T": [
                                1.0280380989998476e-09,
                                7.780728031815311e-12,
                                1.0,
                                5.447821581999192e-07,
                                -0.9999999999998517,
                                7.780167974999871e-12,
                                0.9999999999998517,
                                5.447821581999111e-07,
                                -1.0280381032384968e-09
                            ]
                        },
                        {
                            "NodeNumber": 16951,
                            "Type": 1,
                            "T": [
                                1.0280380989998476e-09,
                                7.780728031815311e-12,
                                1.0,
                                5.447821581999192e-07,
                                -0.9999999999998517,
                                7.780167974999871e-12,
                                0.9999999999998517,
                                5.447821581999111e-07,
                                -1.0280381032384968e-09
                            ]
                        }
                    ],
                    "Entities": [
                        1,
                        2,
                        5
                    ],
                    "EntityTypes": [
                        0,
                        0,
                        1
                    ]
                },
                {
                    "Id": 2,
                    "Name": "Connection3",
                    "Type": 0,
                    "FiniteElementNodes": [
                        16894,
                        16952,
                        16953,
                        16954,
                        16955
                    ],
                    "FiniteElementNodeTransformations": [
                        {
                            "NodeNumber": 16894,
                            "Type": 1,
                            "T": [
                                1.863718069e-10,
                                7.780498583505868e-12,
                                1.0,
                                6.25126025e-10,
                                -1.0,
                                7.780498467e-12,
                                1.0,
                                6.251260249985499e-10,
                                -1.863718069048638e-10
                            ]
                        },
                        {
                            "NodeNumber": 16952,
                            "Type": 1,
                            "T": [
                                1.863718069e-10,
                                7.780498583505868e-12,
                                1.0,
                                6.25126025e-10,
                                -1.0,
                                7.780498467e-12,
                                1.0,
                                6.251260249985499e-10,
                                -1.863718069048638e-10
                            ]
                        },
                        {
                            "NodeNumber": 16953,
                            "Type": 1,
                            "T": [
                                1.863718069e-10,
                                7.780498583505868e-12,
                                1.0,
                                6.25126025e-10,
                                -1.0,
                                7.780498467e-12,
                                1.0,
                                6.251260249985499e-10,
                                -1.863718069048638e-10
                            ]
                        },
                        {
                            "NodeNumber": 16954,
                            "Type": 1,
                            "T": [
                                1.863718069e-10,
                                7.780498583505868e-12,
                                1.0,
                                6.25126025e-10,
                                -1.0,
                                7.780498467e-12,
                                1.0,
                                6.251260249985499e-10,
                                -1.863718069048638e-10
                            ]
                        },
                        {
                            "NodeNumber": 16955,
                            "Type": 1,
                            "T": [
                                1.863718069e-10,
                                7.780498583505868e-12,
                                1.0,
                                6.25126025e-10,
                                -1.0,
                                7.780498467e-12,
                                1.0,
                                6.251260249985499e-10,
                                -1.863718069048638e-10
                            ]
                        }
                    ],
                    "Entities": [
                        2,
                        3,
                        6
                    ],
                    "EntityTypes": [
                        0,
                        0,
                        1
                    ]
                }
            ],
            "SimplifiedCheck": false
        },
        {
            "Id": 2,
            "Name": "panel(Pl504, Pl689, 4)_to_(Pl504, Pl689, 1)",
            "Type": 1,
            "Plates": [
                {
                    "Id": 0,
                    "Name": "Plate(Pl504, Pl689, 4)",
                    "Type": 0,
                    "Material": {
                        "E": 210000000000.0,
                        "G": 80769230769.23077,
                        "fy": 355000000.0,
                        "GammaM": 1.15,
                        "PoissonRatio": 0.3
                    },
                    "Geometry": {
                        "Thickness": 0.016,
                        "Length": 3.999999999999993,
                        "Width": 1.750000000831737
                    },
                    "FiniteElements": [
                        30183,
                        30184,
                        30185,
                        30186,
                        34403,
                        34404,
                        34405,
                        34406
                    ]
                },
                {
                    "Id": 1,
                    "Name": "Plate(Pl504, Pl689, 3)",
                    "Type": 0,
                    "Material": {
                        "E": 210000000000.0,
                        "G": 80769230769.23077,
                        "fy": 355000000.0,
                        "GammaM": 1.15,
                        "PoissonRatio": 0.3
                    },
                    "Geometry": {
                        "Thickness": 0.016,
                        "Length": 4.0,
                        "Width": 1.7500000000000475
                    },
                    "FiniteElements": [
                        30179,
                        30180,
                        30181,
                        30182,
                        34399,
                        34400,
                        34401,
                        34402
                    ]
                },
                {
                    "Id": 2,
                    "Name": "Plate(Pl504, Pl689, 2)",
                    "Type": 0,
                    "Material": {
                        "E": 210000000000.0,
                        "G": 80769230769.23077,
                        "fy": 355000000.0,
                        "GammaM": 1.15,
                        "PoissonRatio": 0.3
                    },
                    "Geometry": {
                        "Thickness": 0.016,
                        "Length": 4.0,
                        "Width": 1.750000000000128
                    },
                    "FiniteElements": [
                        30175,
                        30176,
                        30177,
                        30178,
                        34395,
                        34396,
                        34397,
                        34398
                    ]
                },
                {
                    "Id": 3,
                    "Name": "Plate(Pl504, Pl689, 1)",
                    "Type": 0,
                    "Material": {
                        "E": 210000000000.0,
                        "G": 80769230769.23077,
                        "fy": 355000000.0,
                        "GammaM": 1.15,
                        "PoissonRatio": 0.3
                    },
                    "Geometry": {
                        "Thickness": 0.016,
                        "Length": 3.999999999999993,
                        "Width": 1.7499967356517492
                    },
                    "FiniteElements": [
                        30171,
                        30172,
                        30173,
                        30174,
                        34391,
                        34392,
                        34393,
                        34394
                    ]
                }
            ],
            "Stiffeners": [
                {
                    "Id": 4,
                    "Name": "Stiffener(Pl504, Pl689, 4)",
                    "Type": 1,
                    "StiffenerType": 0,
                    "StiffenerFunction": 0,
                    "StiffenerConnection": 1,
                    "SupportAtFirstCrossSection": 0,
                    "SupportAtSecondCrossSection": 0,
                    "Material": {
                        "E": 210000000000.0,
                        "G": 80769230769.23077,
                        "fy": 355000000.0,
                        "GammaM": 1.15,
                        "PoissonRatio": 0.3
                    },
                    "StiffenerSections": [
                        {
                            "ConnectionNodeId": 16814,
                            "ConnectedSections": [
                                {
                                    "SectionId": 1,
                                    "Orientation": {
                                        "X": 1.0,
                                        "Y": 7.780498467e-12,
                                        "Z": -1.863718069048638e-10
                                    },
                                    "Eccentricity": {
                                        "X": 0.0,
                                        "Y": 0.0,
                                        "Z": 0.0
                                    }
                                }
                            ]
                        },
                        {
                            "ConnectionNodeId": 16883,
                            "ConnectedSections": [
                                {
                                    "SectionId": 1,
                                    "Orientation": {
                                        "X": 1.0,
                                        "Y": 7.780498467e-12,
                                        "Z": -1.863718069048638e-10
                                    },
                                    "Eccentricity": {
                                        "X": 0.0,
                                        "Y": 0.0,
                                        "Z": 0.0
                                    }
                                }
                            ]
                        },
                        {
                            "ConnectionNodeId": 16884,
                            "ConnectedSections": [
                                {
                                    "SectionId": 1,
                                    "Orientation": {
                                        "X": 1.0,
                                        "Y": 7.780498467e-12,
                                        "Z": -1.863718069048638e-10
                                    },
                                    "Eccentricity": {
                                        "X": 0.0,
                                        "Y": 0.0,
                                        "Z": 0.0
                                    }
                                }
                            ]
                        },
                        {
                            "ConnectionNodeId": 16885,
                            "ConnectedSections": [
                                {
                                    "SectionId": 1,
                                    "Orientation": {
                                        "X": 1.0,
                                        "Y": 7.780498467e-12,
                                        "Z": -1.863718069048638e-10
                                    },
                                    "Eccentricity": {
                                        "X": 0.0,
                                        "Y": 0.0,
                                        "Z": 0.0
                                    }
                                }
                            ]
                        },
                        {
                            "ConnectionNodeId": 16886,
                            "ConnectedSections": [
                                {
                                    "SectionId": 1,
                                    "Orientation": {
                                        "X": 1.0,
                                        "Y": 7.780498467e-12,
                                        "Z": -1.863718069048638e-10
                                    },
                                    "Eccentricity": {
                                        "X": 0.0,
                                        "Y": 0.0,
                                        "Z": 0.0
                                    }
                                }
                            ]
                        }
                    ],
                    "Sections": [
                        {
                            "SectionId": 1,
                            "SectionName": "BSRAbulb340x14x49x15x15x4_lump3_333",
                            "SectionType": 7,
                            "SectionParameters": {
                                "FilletRadius": 0.0,
                                "FilletRadiusInner": 0.0,
                                "FlangeThickness": 0.03681991904,
                                "FlangeThicknessBottom": -1.7976931348623157e+308,
                                "FlangeThicknessTop": -1.7976931348623157e+308,
                                "FlangeWidth": 0.209979,
                                "FlangeWidthBottom": -1.7976931348623157e+308,
                                "FlangeWidthBottomOffset": -1.7976931348623157e+308,
                                "FlangeWidthTop": -1.7976931348623157e+308,
                                "FlangeWidthTopOffset": -1.7976931348623157e+308,
                                "Height": 0.34,
                                "OuterDiameter": -1.7976931348623157e+308,
                                "OuterWebThickness": -1.7976931348623157e+308,
                                "Thickness": -1.7976931348623157e+308,
                                "WebSpacing": -1.7976931348623157e+308,
                                "WebThickness": 0.046662,
                                "Width": -1.7976931348623157e+308,
                                "WebOrientation": 0
                            },
                            "SectionGeneral": {
                                "Comp": 0,
                                "Area": 0.02187839871785568,
                                "Ix": 1.3381191480161487e-05,
                                "Iy": 0.00025371632420276215,
                                "Iz": 6.430988166511026e-05,
                                "Iyz": -6.939968399175288e-05,
                                "Wxmin": 0.0002690989006118122,
                                "Wymin": 0.0011986703390250515,
                                "Wzmin": 0.00040756255009306375,
                                "Shary": 0.005165838528621597,
                                "Sharz": 0.011326118539461243,
                                "Shceny": -0.028856560010173667,
                                "Shcenz": -0.10992523495129693,
                                "Sy": 0.001045275226345321,
                                "Sz": 0.00045837372253545143,
                                "Wpy": 0.0,
                                "Wpz": 0.0,
                                "Fabr": 0
                            }
                        }
                    ],
                    "FiniteElements": [
                        16921,
                        16922,
                        16923,
                        16924
                    ]
                },
                {
                    "Id": 5,
                    "Name": "Stiffener(Pl504, Pl689, 3)",
                    "Type": 1,
                    "StiffenerType": 0,
                    "StiffenerFunction": 0,
                    "StiffenerConnection": 1,
                    "SupportAtFirstCrossSection": 0,
                    "SupportAtSecondCrossSection": 0,
                    "Material": {
                        "E": 210000000000.0,
                        "G": 80769230769.23077,
                        "fy": 355000000.0,
                        "GammaM": 1.15,
                        "PoissonRatio": 0.3
                    },
                    "StiffenerSections": [
                        {
                            "ConnectionNodeId": 16820,
                            "ConnectedSections": [
                                {
                                    "SectionId": 2,
                                    "Orientation": {
                                        "X": 1.0,
                                        "Y": 7.780498467e-12,
                                        "Z": -1.863718069048638e-10
                                    },
                                    "Eccentricity": {
                                        "X": 0.0,
                                        "Y": 0.0,
                                        "Z": 0.0
                                    }
                                }
                            ]
                        },
                        {
                            "ConnectionNodeId": 16887,
                            "ConnectedSections": [
                                {
                                    "SectionId": 2,
                                    "Orientation": {
                                        "X": 1.0,
                                        "Y": 7.780498467e-12,
                                        "Z": -1.863718069048638e-10
                                    },
                                    "Eccentricity": {
                                        "X": 0.0,
                                        "Y": 0.0,
                                        "Z": 0.0
                                    }
                                }
                            ]
                        },
                        {
                            "ConnectionNodeId": 16888,
                            "ConnectedSections": [
                                {
                                    "SectionId": 2,
                                    "Orientation": {
                                        "X": 1.0,
                                        "Y": 7.780498467e-12,
                                        "Z": -1.863718069048638e-10
                                    },
                                    "Eccentricity": {
                                        "X": 0.0,
                                        "Y": 0.0,
                                        "Z": 0.0
                                    }
                                }
                            ]
                        },
                        {
                            "ConnectionNodeId": 16889,
                            "ConnectedSections": [
                                {
                                    "SectionId": 2,
                                    "Orientation": {
                                        "X": 1.0,
                                        "Y": 7.780498467e-12,
                                        "Z": -1.863718069048638e-10
                                    },
                                    "Eccentricity": {
                                        "X": 0.0,
                                        "Y": 0.0,
                                        "Z": 0.0
                                    }
                                }
                            ]
                        },
                        {
                            "ConnectionNodeId": 16890,
                            "ConnectedSections": [
                                {
                                    "SectionId": 2,
                                    "Orientation": {
                                        "X": 1.0,
                                        "Y": 7.780498467e-12,
                                        "Z": -1.863718069048638e-10
                                    },
                                    "Eccentricity": {
                                        "X": 0.0,
                                        "Y": 0.0,
                                        "Z": 0.0
                                    }
                                }
                            ]
                        }
                    ],
                    "Sections": [
                        {
                            "SectionId": 2,
                            "SectionName": "BSRAbulb340x14x49x15x15x4_lump3_333",
                            "SectionType": 7,
                            "SectionParameters": {
                                "FilletRadius": 0.0,
                                "FilletRadiusInner": 0.0,
                                "FlangeThickness": 0.03681991904,
                                "FlangeThicknessBottom": -1.7976931348623157e+308,
                                "FlangeThicknessTop": -1.7976931348623157e+308,
                                "FlangeWidth": 0.209979,
                                "FlangeWidthBottom": -1.7976931348623157e+308,
                                "FlangeWidthBottomOffset": -1.7976931348623157e+308,
                                "FlangeWidthTop": -1.7976931348623157e+308,
                                "FlangeWidthTopOffset": -1.7976931348623157e+308,
                                "Height": 0.34,
                                "OuterDiameter": -1.7976931348623157e+308,
                                "OuterWebThickness": -1.7976931348623157e+308,
                                "Thickness": -1.7976931348623157e+308,
                                "WebSpacing": -1.7976931348623157e+308,
                                "WebThickness": 0.046662,
                                "Width": -1.7976931348623157e+308,
                                "WebOrientation": 0
                            },
                            "SectionGeneral": {
                                "Comp": 0,
                                "Area": 0.02187839871785568,
                                "Ix": 1.3381191480161487e-05,
                                "Iy": 0.00025371632420276215,
                                "Iz": 6.430988166511026e-05,
                                "Iyz": -6.939968399175288e-05,
                                "Wxmin": 0.0002690989006118122,
                                "Wymin": 0.0011986703390250515,
                                "Wzmin": 0.00040756255009306375,
                                "Shary": 0.005165838528621597,
                                "Sharz": 0.011326118539461243,
                                "Shceny": -0.028856560010173667,
                                "Shcenz": -0.10992523495129693,
                                "Sy": 0.001045275226345321,
                                "Sz": 0.00045837372253545143,
                                "Wpy": 0.0,
                                "Wpz": 0.0,
                                "Fabr": 0
                            }
                        }
                    ],
                    "FiniteElements": [
                        16925,
                        16926,
                        16927,
                        16928
                    ]
                },
                {
                    "Id": 6,
                    "Name": "Stiffener(Pl504, Pl689, 2)",
                    "Type": 1,
                    "StiffenerType": 0,
                    "StiffenerFunction": 0,
                    "StiffenerConnection": 1,
                    "SupportAtFirstCrossSection": 0,
                    "SupportAtSecondCrossSection": 0,
                    "Material": {
                        "E": 210000000000.0,
                        "G": 80769230769.23077,
                        "fy": 355000000.0,
                        "GammaM": 1.15,
                        "PoissonRatio": 0.3
                    },
                    "StiffenerSections": [
                        {
                            "ConnectionNodeId": 16824,
                            "ConnectedSections": [
                                {
                                    "SectionId": 3,
                                    "Orientation": {
                                        "X": 1.0,
                                        "Y": 7.780498467e-12,
                                        "Z": -1.863718069048638e-10
                                    },
                                    "Eccentricity": {
                                        "X": 0.0,
                                        "Y": 0.0,
                                        "Z": 0.0
                                    }
                                }
                            ]
                        },
                        {
                            "ConnectionNodeId": 16891,
                            "ConnectedSections": [
                                {
                                    "SectionId": 3,
                                    "Orientation": {
                                        "X": 1.0,
                                        "Y": 7.780498467e-12,
                                        "Z": -1.863718069048638e-10
                                    },
                                    "Eccentricity": {
                                        "X": 0.0,
                                        "Y": 0.0,
                                        "Z": 0.0
                                    }
                                }
                            ]
                        },
                        {
                            "ConnectionNodeId": 16892,
                            "ConnectedSections": [
                                {
                                    "SectionId": 3,
                                    "Orientation": {
                                        "X": 1.0,
                                        "Y": 7.780498467e-12,
                                        "Z": -1.863718069048638e-10
                                    },
                                    "Eccentricity": {
                                        "X": 0.0,
                                        "Y": 0.0,
                                        "Z": 0.0
                                    }
                                }
                            ]
                        },
                        {
                            "ConnectionNodeId": 16893,
                            "ConnectedSections": [
                                {
                                    "SectionId": 3,
                                    "Orientation": {
                                        "X": 1.0,
                                        "Y": 7.780498467e-12,
                                        "Z": -1.863718069048638e-10
                                    },
                                    "Eccentricity": {
                                        "X": 0.0,
                                        "Y": 0.0,
                                        "Z": 0.0
                                    }
                                }
                            ]
                        },
                        {
                            "ConnectionNodeId": 16894,
                            "ConnectedSections": [
                                {
                                    "SectionId": 3,
                                    "Orientation": {
                                        "X": 1.0,
                                        "Y": 7.780498467e-12,
                                        "Z": -1.863718069048638e-10
                                    },
                                    "Eccentricity": {
                                        "X": 0.0,
                                        "Y": 0.0,
                                        "Z": 0.0
                                    }
                                }
                            ]
                        }
                    ],
                    "Sections": [
                        {
                            "SectionId": 3,
                            "SectionName": "BSRAbulb340x14x49x15x15x4_lump3_333",
                            "SectionType": 7,
                            "SectionParameters": {
                                "FilletRadius": 0.0,
                                "FilletRadiusInner": 0.0,
                                "FlangeThickness": 0.03681991904,
                                "FlangeThicknessBottom": -1.7976931348623157e+308,
                                "FlangeThicknessTop": -1.7976931348623157e+308,
                                "FlangeWidth": 0.209979,
                                "FlangeWidthBottom": -1.7976931348623157e+308,
                                "FlangeWidthBottomOffset": -1.7976931348623157e+308,
                                "FlangeWidthTop": -1.7976931348623157e+308,
                                "FlangeWidthTopOffset": -1.7976931348623157e+308,
                                "Height": 0.34,
                                "OuterDiameter": -1.7976931348623157e+308,
                                "OuterWebThickness": -1.7976931348623157e+308,
                                "Thickness": -1.7976931348623157e+308,
                                "WebSpacing": -1.7976931348623157e+308,
                                "WebThickness": 0.046662,
                                "Width": -1.7976931348623157e+308,
                                "WebOrientation": 0
                            },
                            "SectionGeneral": {
                                "Comp": 0,
                                "Area": 0.02187839871785568,
                                "Ix": 1.3381191480161487e-05,
                                "Iy": 0.00025371632420276215,
                                "Iz": 6.430988166511026e-05,
                                "Iyz": -6.939968399175288e-05,
                                "Wxmin": 0.0002690989006118122,
                                "Wymin": 0.0011986703390250515,
                                "Wzmin": 0.00040756255009306375,
                                "Shary": 0.005165838528621597,
                                "Sharz": 0.011326118539461243,
                                "Shceny": -0.028856560010173667,
                                "Shcenz": -0.10992523495129693,
                                "Sy": 0.001045275226345321,
                                "Sz": 0.00045837372253545143,
                                "Wpy": 0.0,
                                "Wpz": 0.0,
                                "Fabr": 0
                            }
                        }
                    ],
                    "FiniteElements": [
                        16929,
                        16930,
                        16931,
                        16932
                    ]
                }
            ],
            "Connections": [
                {
                    "Id": 0,
                    "Name": "Connection1",
                    "Type": 0,
                    "FiniteElementNodes": [
                        16814,
                        16883,
                        16884,
                        16885,
                        16886
                    ],
                    "FiniteElementNodeTransformations": [
                        {
                            "NodeNumber": 16814,
                            "Type": 1,
                            "T": [
                                1.863718069e-10,
                                7.780498583505868e-12,
                                1.0,
                                6.25126025e-10,
                                -1.0,
                                7.780498467e-12,
                                1.0,
                                6.251260249985499e-10,
                                -1.863718069048638e-10
                            ]
                        },
                        {
                            "NodeNumber": 16883,
                            "Type": 1,
                            "T": [
                                1.863718069e-10,
                                7.780498583505868e-12,
                                1.0,
                                6.25126025e-10,
                                -1.0,
                                7.780498467e-12,
                                1.0,
                                6.251260249985499e-10,
                                -1.863718069048638e-10
                            ]
                        },
                        {
                            "NodeNumber": 16884,
                            "Type": 1,
                            "T": [
                                1.863718069e-10,
                                7.780498583505868e-12,
                                1.0,
                                6.25126025e-10,
                                -1.0,
                                7.780498467e-12,
                                1.0,
                                6.251260249985499e-10,
                                -1.863718069048638e-10
                            ]
                        },
                        {
                            "NodeNumber": 16885,
                            "Type": 1,
                            "T": [
                                1.863718069e-10,
                                7.780498583505868e-12,
                                1.0,
                                6.25126025e-10,
                                -1.0,
                                7.780498467e-12,
                                1.0,
                                6.251260249985499e-10,
                                -1.863718069048638e-10
                            ]
                        },
                        {
                            "NodeNumber": 16886,
                            "Type": 1,
                            "T": [
                                1.863718069e-10,
                                7.780498583505868e-12,
                                1.0,
                                6.25126025e-10,
                                -1.0,
                                7.780498467e-12,
                                1.0,
                                6.251260249985499e-10,
                                -1.863718069048638e-10
                            ]
                        }
                    ],
                    "Entities": [
                        0,
                        1,
                        4
                    ],
                    "EntityTypes": [
                        0,
                        0,
                        1
                    ]
                },
                {
                    "Id": 1,
                    "Name": "Connection2",
                    "Type": 0,
                    "FiniteElementNodes": [
                        16820,
                        16887,
                        16888,
                        16889,
                        16890
                    ],
                    "FiniteElementNodeTransformations": [
                        {
                            "NodeNumber": 16820,
                            "Type": 1,
                            "T": [
                                1.863718069e-10,
                                7.780498583505868e-12,
                                1.0,
                                6.25126025e-10,
                                -1.0,
                                7.780498467e-12,
                                1.0,
                                6.251260249985499e-10,
                                -1.863718069048638e-10
                            ]
                        },
                        {
                            "NodeNumber": 16887,
                            "Type": 1,
                            "T": [
                                1.863718069e-10,
                                7.780498583505868e-12,
                                1.0,
                                6.25126025e-10,
                                -1.0,
                                7.780498467e-12,
                                1.0,
                                6.251260249985499e-10,
                                -1.863718069048638e-10
                            ]
                        },
                        {
                            "NodeNumber": 16888,
                            "Type": 1,
                            "T": [
                                1.863718069e-10,
                                7.780498583505868e-12,
                                1.0,
                                6.25126025e-10,
                                -1.0,
                                7.780498467e-12,
                                1.0,
                                6.251260249985499e-10,
                                -1.863718069048638e-10
                            ]
                        },
                        {
                            "NodeNumber": 16889,
                            "Type": 1,
                            "T": [
                                1.863718069e-10,
                                7.780498583505868e-12,
                                1.0,
                                6.25126025e-10,
                                -1.0,
                                7.780498467e-12,
                                1.0,
                                6.251260249985499e-10,
                                -1.863718069048638e-10
                            ]
                        },
                        {
                            "NodeNumber": 16890,
                            "Type": 1,
                            "T": [
                                1.863718069e-10,
                                7.780498583505868e-12,
                                1.0,
                                6.25126025e-10,
                                -1.0,
                                7.780498467e-12,
                                1.0,
                                6.251260249985499e-10,
                                -1.863718069048638e-10
                            ]
                        }
                    ],
                    "Entities": [
                        1,
                        2,
                        5
                    ],
                    "EntityTypes": [
                        0,
                        0,
                        1
                    ]
                },
                {
                    "Id": 2,
                    "Name": "Connection3",
                    "Type": 0,
                    "FiniteElementNodes": [
                        16824,
                        16891,
                        16892,
                        16893,
                        16894
                    ],
                    "FiniteElementNodeTransformations": [
                        {
                            "NodeNumber": 16824,
                            "Type": 1,
                            "T": [
                                1.863718069e-10,
                                7.780498583505868e-12,
                                1.0,
                                6.25126025e-10,
                                -1.0,
                                7.780498467e-12,
                                1.0,
                                6.251260249985499e-10,
                                -1.863718069048638e-10
                            ]
                        },
                        {
                            "NodeNumber": 16891,
                            "Type": 1,
                            "T": [
                                1.863718069e-10,
                                7.780498583505868e-12,
                                1.0,
                                6.25126025e-10,
                                -1.0,
                                7.780498467e-12,
                                1.0,
                                6.251260249985499e-10,
                                -1.863718069048638e-10
                            ]
                        },
                        {
                            "NodeNumber": 16892,
                            "Type": 1,
                            "T": [
                                1.863718069e-10,
                                7.780498583505868e-12,
                                1.0,
                                6.25126025e-10,
                                -1.0,
                                7.780498467e-12,
                                1.0,
                                6.251260249985499e-10,
                                -1.863718069048638e-10
                            ]
                        },
                        {
                            "NodeNumber": 16893,
                            "Type": 1,
                            "T": [
                                1.863718069e-10,
                                7.780498583505868e-12,
                                1.0,
                                6.25126025e-10,
                                -1.0,
                                7.780498467e-12,
                                1.0,
                                6.251260249985499e-10,
                                -1.863718069048638e-10
                            ]
                        },
                        {
                            "NodeNumber": 16894,
                            "Type": 1,
                            "T": [
                                1.863718069e-10,
                                7.780498583505868e-12,
                                1.0,
                                6.25126025e-10,
                                -1.0,
                                7.780498467e-12,
                                1.0,
                                6.251260249985499e-10,
                                -1.863718069048638e-10
                            ]
                        }
                    ],
                    "Entities": [
                        2,
                        3,
                        6
                    ],
                    "EntityTypes": [
                        0,
                        0,
                        1
                    ]
                }
            ],
            "SimplifiedCheck": false
        }
    ]
}